langchain_nexus/__init__.py
langchain_nexus/models/__init__.py
langchain_nexus/models/chat_openai.py
langchain_nexus/models/chat_zhipuai.py
langchain_nexus/models/embedding.py
tests/__init__.py
langchain_nexus-0.0.0.dist-info/LICENSE
langchain_nexus-0.0.0.dist-info/METADATA
langchain_nexus-0.0.0.dist-info/WHEEL
langchain_nexus-0.0.0.dist-info/top_level.txt
langchain_nexus-0.0.0.dist-info/RECORD
