Metadata-Version: 2.1
Name: langchain_nexus
Version: 0.0.0
Summary: Langchain-Nexus is a Python library enabling easy integration with diverse language models like ChatGPT and GLM through a unified interface.
Home-page: https://github.com/Security-Product/langchain-nexus
Author: geb
Author-email: 853934146@qq.com
Classifier: Programming Language :: Python :: 3
Classifier: Operating System :: OS Independent
Requires-Python: >=3.10
License-File: LICENSE
Requires-Dist: langchain
Requires-Dist: openai
Requires-Dist: zhipuai
Requires-Dist: langchain-openai
